README.md
setup.cfg
setup.py
pygamemaq/__init__.py
pygamemaq/utils.py
pygamemaq.egg-info/PKG-INFO
pygamemaq.egg-info/SOURCES.txt
pygamemaq.egg-info/dependency_links.txt
pygamemaq.egg-info/not-zip-safe
pygamemaq.egg-info/top_level.txt