Metadata-Version: 1.1
Name: pygamemaq
Version: 0.1
Summary: Pygame interface
Home-page: https://github.com/papibenjie/pygamemaq
Author: Marc-Antoine Quessu
Author-email: papibenjie@gmail.com
License: UNKNOWN
Download-URL: https://github.com/papibenjie/pygamemaq/archive/0.1.tar.gz
Platform: UNKNOWN
